Workbook

Sheet Leeme
A1: TP3 IO II · RedBaires · modelo de datos
A3: Estado | B3: 25/9/2026. Todo sale de muestra_cascadas_REDBAIRES.csv sin las 132 filas duplicadas y de parametros_y_costos.csv.
A4: Base de las medias | B4: Las medias de hijos (R) excluyen las 14 cascadas cortadas en 500 eventos (D14), así que algunas difieren un poco de las del README.
A5: Colores | B5: Azul: dato medido o del CSV, cargado a mano. Negro: fórmula. Verde: fórmula que trae un valor de otra hoja. Amarillo: para completar por el grupo.
A6: Modelo de datos | B6: La tabla con el formato de la clase 06: variable, U.M., valor, tipo de función, parámetros y relación. Una fila por elemento del modelo conceptual.
A7: Parámetros CSV | B7: parametros_y_costos.csv tal cual, con valor base y rango.
A8: Llegadas | B8: Semillas por hora del día y por día de la semana, y la tasa por hora que sale de ahí.
A9: Tipos de cuenta | B9: Mezcla de tipos en semillas y en reenvíos, hijos medios (R) y seguidores por tipo.
A10: Generaciones | B10: Hijos medios por generación: el decaimiento (D18).
A11: Marca | B11: Probabilidad de que Centinela marque, por tema y quintil de toxicidad.
A12: Ajuste D19 | B12: Ajuste de distribuciones al tiempo entre generaciones.
A13: Validación | B13: Los números que el simulador tiene que reproducir.
A14: A priori | B14: Cuentas sin simular: tamaño esperado, ocupación del moderador y tipo de cambio. Son fórmulas sobre las otras hojas.
... A17: Decisiones | B17: D1 a D20, como en el README y el artifact. La columna amarilla es para lo que elija el grupo.

Sheet Modelo de datos
A1: Modelo de datos
A2: Formato de la clase 06: la cuantificación de cada elemento definido en el modelo conceptual. Los valores verdes vienen de las otras hojas.
A3: Elemento | B3: Variable | C3: Descripción | D3: U.M. | E3: Valor | F3: Tipo de función | G3: Parámetros | H3: Relación / Expresión | I3: Estado
A4: Entidad | B4: Llegada de rumores | C4: tiempo entre semillas | D4: 1/hora | E4: =Llegadas!$C$30 | F4: Exponencial | G4: λ según la hora del día: hoja Llegadas | I4: propuesta · D15
A5: Entidad | B5: Tipo de cuenta de la semilla | C5: con qué cuenta arranca la cascada | D5: tipo | F5: Discreta | G5: BROADCASTER 12 % · CREATOR 17 % · AGGREGATOR 18 % · LURKER 15 % · STANDARD 39 % | I5: medido
A6: Atributo | B6: Frente n[tipo] | C6: reenvíos vivos de cada tipo en la generación g | D6: reenvíos | F6: Multinomial | G6: mezcla de reenvíos: hoja Tipos de cuenta | I6: propuesta · D17
A7: Actividad | B7: Hijos del frente | C7: reenvíos que genera el frente | D7: reenvíos | E7: ='Tipos de cuenta'!$D$9 | F7: Poisson | G7: Λ | H7: Λ = Σ nᵢ · Rᵢ · δ(g) | I7: propuesta · D16
A8: Parámetro | B8: R BROADCASTER | C8: hijos medios por evento | D8: hijos | E8: ='Tipos de cuenta'!$D$4 | I8: medido
A9: Parámetro | B9: R CREATOR | C9: hijos medios por evento | D9: hijos | E9: ='Tipos de cuenta'!$D$5 | I9: medido
A10: Parámetro | B10: R AGGREGATOR · LURKER · STANDARD | C10: hijos medios por evento | D10: hijos | E10: ='Tipos de cuenta'!$D$8 | G10: los tres ~0,59 | I10: medido
A11: Parámetro | B11: δ(g) | C11: decaimiento por generación | D11: factor | F11: Tabla | G11: hoja Generaciones: de 2,35 en g=0 a 0,37 en g=11 | I11: propuesta · D18
A12: Atributo | B12: Seguidores | C12: audiencia de quien reenvía | D12: seguidores | F12: Empírica por tipo | G12: mediana: BROADCASTER 422 mil · CREATOR 101 mil · resto ~410 | I12: medido
A13: Actividad | B13: Impresiones | C13: cuántos ven el reenvío | D13: impresiones | E13: ='A priori'!$C$5 | F13: Determinística | H13: impresiones = 0,15 × seguidores | I13: medido
A14: Actividad | B14: Tiempo entre generaciones | C14: demora hasta el frente siguiente | D14: min | E14: 43 | F14: Gamma | G14: forma 0,55 · escala 128 min | I14: abierta · D19
A15: Evento | B15: Marca de Centinela | C15: si el reenvío entra a la cola | D15: prob. | E15: =Marca!$B$9 | F15: Bernoulli | G15: p según tema y quintil de toxicidad: hoja Marca | I15: propuesta
A16: Atributo | B16: Nocivo | C16: si la impresión cuesta o rinde | D16: sí / no | H16: tema DISARM | I16: abierta · D8
A17: Atributo | B17: Coordinada | C17: si la cascada es de campaña | D17: sí / no | F17: Bernoulli | G17: precisión y recall de la detección | H17: sufijo C2 + cuenta nueva | I17: propuesta · D11
A18: Recurso | B18: Moderadores por turno (c) | C18: capacidad del único recurso | D18: moderadores | E18: ='Parámetros CSV'!$B$6 | F18: VD | G18: rango 1 – 12 | I18: del CSV
A19: Actividad | B19: Tiempo de revisión | C19: atención de un ítem de moderación con k marcados | D19: seg | E19: ='A priori'!$C$13 | F19: Erlang | G19: k fases de ~20 s | H19: 20 s = 0,12 USD ÷ 22 USD/h | I19: propuesta · D20
A20: Cola | B20: Cola de moderación | C20: ítems marcados esperando | D20: ítems | F20: FIFO | G20: prioridad como escenario | I20: propuesta · D9
A21: Evento | B21: Remoción | C21: fracción del frente que se corta | D21: fracción | F21: Bernoulli por ítem | G21: más baja para verificadas | H21: frente × (1 − fracción removida) | I21: propuesta · D10
A22: VD | B22: Límite de reenvíos: umbral | C22: a partir de qué reenvío actúa | D22: reenvíos | E22: ='Parámetros CSV'!$B$18 | F22: VD | G22: rango 1 – 20 | I22: del CSV · D13
A23: VD | B23: Límite de reenvíos: reducción | C23: cuánto baja la descendencia | D23: fracción | E23: ='Parámetros CSV'!$B$17 | F23: VD | G23: rango 0 – 0,9 | H23: Λ × (1 − reducción) | I23: del CSV
A24: Parámetro | B24: Pérdida de engagement por fricción | C24: engagement legítimo perdido | D24: fracción | E24: ='Parámetros CSV'!$B$19 | G24: rango 0,02 – 0,5 | I24: del CSV
A25: VD | B25: Degradación de alcance | C25: costo por cuenta degradada | D25: USD/día | E25: ='Parámetros CSV'!$B$20 | F25: VD | G25: rango 20 – 600 | I25: del CSV · D12
A26: VD | B26: Clasificador: precisión | C26: fracción de marcas correctas | D26: fracción | E26: ='Parámetros CSV'!$B$13 | F26: VD | G26: rango 0,5 – 0,95 | I26: del CSV
A27: VD | B27: Clasificador: recall | C27: fracción de nocivos detectados | D27: fracción | E27: ='Parámetros CSV'!$B$14 | F27: VD | G27: rango 0,3 – 0,9 | I27: del CSV
A28: Validación | B28: Latencia de moderación | C28: minutos hasta la acción | D28: min | E28: =Validación!$B$15 | G28: piso 90 · p90 381 | H28: salida, no entrada | I28: medido · D7
A29: Validación | B29: SLA de moderación | C29: latencia objetivo | D29: min | E29: ='Parámetros CSV'!$B$21 | G29: rango 30 – 720 | I29: del CSV

Sheet Parámetros CSV
A1: Parámetros y costos del CSV de la cátedra
A3: Parámetro | B3: Valor base | C3: Unidad | D3: Mínimo | E3: Máximo | F3: Comentario del CSV
A4: valor_engagement_por_impresion | B4: 0.0009 | C4: USD/impresion | D4: 0.0003 | E4: 0.003 | F4: Valor economico atribuido por impresion legitima (ingreso publicitario proxy)
A5: costo_moderador_por_hora | B5: 22 | C5: USD/hora | D5: 14 | E5: 45 | F5: Costo cargado de un moderador de contenido humano
A6: moderadores_por_turno | B6: 1 | C6: count | D6: 1 | E6: 12 | F6: Cantidad de moderadores simultaneos por turno evaluados
A7: horas_operativas_mes | B7: 720 | C7: horas/mes | D7: 672 | E7: 744 | F7: Horas operativas por mes (aprox 24/7)
A8: costo_revision_por_item_flag | B8: 0.12 | C8: USD/item | D8: 0.05 | E8: 0.6 | F8: Costo marginal de revisar un item marcado por el clasificador
A9: capex_clasificador_ml | B9: 250000 | C9: USD | D9: 80000 | E9: 900000 | F9: Costo de desarrollar/adquirir el clasificador automatico de contenido
A10: opex_anual_clasificador | B10: 60000 | C10: USD/year | D10: 20000 | E10: 180000 | F10: Costo anual de operacion/reentrenamiento del clasificador
A11: vida_util_clasificador_years | B11: 4 | C11: years | D11: 2 | E11: 8 | F11: Vida util para amortizar el clasificador
A12: discount_rate | B12: 0.1 | C12: decimal | D12: 0.06 | E12: 0.18 | F12: Tasa de descuento para NPV
A13: precision_clasificador | B13: 0.72 | C13: fraction | D13: 0.5 | E13: 0.95 | F13: Precision del clasificador (fraccion de flags correctos)
A14: recall_clasificador | B14: 0.63 | C14: fraction | D14: 0.3 | E14: 0.9 | F14: Recall del clasificador (fraccion de nocivos detectados)
A15: costo_reputacional_por_falso_positivo | B15: 1.5 | C15: USD/item | D15: 0.2 | E15: 10 | F15: Costo de moderar de mas contenido legitimo (usuarios molestos, apelaciones)
... A23: tasa_churn_por_exposicion_nociva | B23: 0.0006 | C23: fraction | D23: 0.0001 | E23: 0.004 | F23: Incremento de churn por exposicion a contenido nocivo no moderado

Sheet Llegadas
A1: Llegadas de rumores (semillas)
A2: Días que cubre la muestra en C3. La tasa es una fórmula: semillas en esa hora ÷ días.
A3: Días de la muestra | C3: 180
A5: Hora del día | B5: Semillas en la muestra | C5: Tasa (semillas por hora)
A6: 00:00 | B6: 118 | C6: =B6/$C$3
A7: 01:00 | B7: 110 | C7: =B7/$C$3
A8: 02:00 | B8: 98 | C8: =B8/$C$3
A9: 03:00 | B9: 91 | C9: =B9/$C$3
A10: 04:00 | B10: 116 | C10: =B10/$C$3
A11: 05:00 | B11: 122 | C11: =B11/$C$3
A12: 06:00 | B12: 167 | C12: =B12/$C$3
A13: 07:00 | B13: 209 | C13: =B13/$C$3
A14: 08:00 | B14: 221 | C14: =B14/$C$3
A15: 09:00 | B15: 214 | C15: =B15/$C$3
A16: 10:00 | B16: 290 | C16: =B16/$C$3
A17: 11:00 | B17: 279 | C17: =B17/$C$3
... A29: 23:00 | B29: 171 | C29: =B29/$C$3
A30: Total | B30: =SUM(B6:B29) | C30: =B30/$C$3/24
A31: La tasa del total es el promedio por hora a lo largo del día.
A32: Por día de la semana
A33: Día | B33: Semillas en la muestra | C33: Semillas por día
A34: lunes | B34: 714 | C34: =B34/($C$3/7)
A35: martes | B35: 675 | C35: =B35/($C$3/7)
A36: miércoles | B36: 696 | C36: =B36/($C$3/7)
A37: jueves | B37: 626 | C37: =B37/($C$3/7)
A38: viernes | B38: 670 | C38: =B38/($C$3/7)
A39: sábado | B39: 813 | C39: =B39/($C$3/7)
A40: domingo | B40: 806 | C40: =B40/($C$3/7)

Sheet Tipos de cuenta
A1: Tipos de cuenta
A2: R = hijos medios por evento (reshare_count_from_actor), sin las 14 cascadas truncadas.
A3: Tipo | B3: % de las semillas | C3: % de los reenvíos | D3: Hijos medios (R) | E3: Seguidores: p10 | F3: Seguidores: mediana | G3: Seguidores: p90 | H3: Impresiones esperadas (mediana)
A4: BROADCASTER | B4: 0.1198 | C4: 0.0368 | D4: 4.444 | E4: 233582 | F4: 422345 | G4: 1100000 | H4: =F4*'A priori'!$C$5
A5: CREATOR | B5: 0.1654 | C5: 0.0632 | D5: 3.525 | E5: 58122 | F5: 101192 | G5: 182000 | H5: =F5*'A priori'!$C$5
A6: AGGREGATOR | B6: 0.1774 | C6: 0.2198 | D6: 0.58 | E6: 315 | F6: 410 | G6: 1118 | H6: =F6*'A priori'!$C$5
A7: LURKER | B7: 0.1478 | C7: 0.1919 | D7: 0.587 | E7: 320 | F7: 410 | G7: 1131 | H7: =F7*'A priori'!$C$5
A8: STANDARD | B8: 0.3896 | C8: 0.4882 | D8: 0.591 | E8: 315 | F8: 416 | G8: 1100 | H8: =F8*'A priori'!$C$5
A9: Total | B9: =SUM(B4:B8) | C9: =SUM(C4:C8) | D9: =SUMPRODUCT(C4:C8,D4:D8)
A10: El R total (D9) es el promedio ponderado por la mezcla de reenvíos. Tiene que dar cerca de 0,916.

Sheet Generaciones
A1: Hijos medios por generación
A2: El decaimiento δ(g) sale de acá. Cómo se normaliza queda para el grupo (D18). La generación 0 es la semilla y tiene más BROADCASTER.
A3: Generación g | B3: Eventos | C3: Hijos medios | D3: Relativo a g = 1
A4: 0 | B4: 4986 | C4: 2.346 | D4: =C4/$C$5
A5: 1 | B5: 11697 | C5: 1.005 | D5: =C5/$C$5
A6: 2 | B6: 11755 | C6: 0.848 | D6: =C6/$C$5
A7: 3 | B7: 9963 | C7: 0.777 | D7: =C7/$C$5
A8: 4 | B8: 7743 | C8: 0.676 | D8: =C8/$C$5
A9: 5 | B9: 5238 | C9: 0.643 | D9: =C9/$C$5
A10: 6 | B10: 3370 | C10: 0.628 | D10: =C10/$C$5
A11: 7 | B11: 2116 | C11: 0.554 | D11: =C11/$C$5
A12: 8 | B12: 1173 | C12: 0.491 | D12: =C12/$C$5
A13: 9 | B13: 576 | C13: 0.439 | D13: =C13/$C$5
A14: 10 | B14: 253 | C14: 0.387 | D14: =C14/$C$5
A15: 11 | B15: 98 | C15: 0.367 | D15: =C15/$C$5
... A19: 15 | B19: 3 | C19: 0 | D19: =C19/$C$5

Sheet Marca
A1: Probabilidad de marca de Centinela
A2: Fracción de eventos con moderation_flag = 1, por grupo de tema y quintil de toxicity_index. Nocivo = DISARM es la hipótesis de D8.
A3: Grupo de tema | B3: Q1 | C3: Q2 | D3: Q3 | E3: Q4 | F3: Q5 | G3: Total del grupo
A4: DISARM | B4: 0.204 | C4: 0.249 | D4: 0.302 | E4: 0.343 | F4: 0.4 | G4: 0.328
A5: ORG | B5: 0.091 | C5: 0.128 | D5: 0.173 | E5: 0.211 | F5: 0.26 | G5: 0.156
A6: Toxicidad del quintil | B6: 0.000 – 0.170 | C6: 0.170 – 0.284 | D6: 0.284 – 0.393 | E6: 0.393 – 0.523 | F6: 0.523 – 1.000
A8: Marcados en la muestra | B8: 15445
A9: Fracción marcada | B9: 0.225

Sheet Ajuste D19
A1: Tiempo entre generaciones (inter_event_time_min > 0)
A2: 60.754 tiempos. Con tantos datos ninguna pasa el test de KS: importa cuál se acerca más. Falta repetirlo con el Input Analyzer.
A3: Distribución | B3: Parámetro 1 | C3: Parámetro 2 | D3: KS (D) | E3: Nota
A4: Gamma | B4: forma 0,55 | C4: escala 128 min | D4: 0.08 | E4: la que mejor ajusta
A5: Weibull | B5: forma 0,67 | C5: escala 53 min | D5: 0.106
A6: Lognormal | B6: σ 1,98 | C6: mediana 22 min | D6: 0.142
A7: Exponencial = Erlang k=1 | B7: media 70 min | D7: 0.151 | E7: la que peor ajusta de las cuatro
A8: Erlang k=2 | B8: media 70 min | D8: 0.274 | E8: una Erlang tiene CV ≤ 1 y estos datos tienen 3,9
A10: Mediana · p90 | B10: 43 min | C10: 151 min
A11: Media · desvío | B11: 70 min | C11: 271 min
A12: Coef. de variación | B12: 3,9 | C12: 1,18 sin el 1 % más extremo

Sheet Validación
A1: Lo que el simulador tiene que reproducir
A2: Con la dotación de hoy, y cortando las cascadas simuladas en 500 como el export.
A3: Métrica | B3: Observado | C3: Unidad | D3: Nota
A4: Cascadas | B4: 5000 | C4: cascadas
A5: Cascadas de un solo evento | B5: 0.4038 | C5: % | D5: 2.019 de 5.000
A6: Tamaño medio | B6: 13.2 | C6: eventos | D6: con las truncadas
A7: Tamaño mediano | B7: 2 | C7: eventos
A8: Tamaño p90 | B8: 29 | C8: eventos
A9: Tamaño p99 | B9: 188 | C9: eventos | D9: el test que manda para D16 y D17
A10: Tamaño máximo | B10: 500 | C10: eventos | D10: tope del export
A11: Profundidad máxima: mediana · p90 · p99 | B11: 1 · 5 · 10 | C11: generaciones
A12: Hijos por evento (R), sin truncadas | B12: 0.916 | C12: hijos
A13: Varianza / media de los hijos | B13: 5.1 | D13: sobredispersión
A14: Fracción marcada por Centinela | B14: 0.225 | C14: %
A15: Latencia de moderación: mediana | B15: 139.9 | C15: min | D15: salida, no entrada: con la escala de D7
A16: Latencia de moderación: p90 | B16: 381.1 | C16: min
A17: Latencia de moderación: piso | B17: 90 | C17: min | D17: ninguna baja de 90
A18: Impresiones / seguidores | B18: 0.15 | D18: igual en los cinco tipos

Sheet A priori
A1: Cuentas sin simular
A2: Todo es fórmula. Cambiá los valores azules o los de 'Parámetros CSV' y se recalcula.
A3: Qué | B3: Fórmula | C3: Valor | D3: Nota
A4: R de todas las cascadas | B4: medido | C4: 0.916
A5: Impresiones / seguidores | B5: medido | C5: 0.15 | D5: lo usa la hoja Tipos de cuenta
A6: Tamaño esperado de una cascada | B6: 1 / (1 − R) | C6: =1/(1-C4) | D6: 11,84 medido
A7: R de las campañas C2 | B7: estimado | C7: 0.977 | D7: sale de 1 − 1/42,8
A8: Tamaño esperado de una campaña C2 | B8: 1 / (1 − R C2) | C8: =1/(1-C7) | D8: 42,8 medido, subestimado por el tope de 500
A9: R de C2 si una palanca la baja a | B9: escenario | C9: 0.95 | D9: cambiar para probar
A10: Tamaño esperado con esa palanca | B10: 1 / (1 − R) | C10: =1/(1-C9) | D10: de 43 pasa a 20: se parte a la mitad
A11: Días de la muestra | B11: Llegadas | C11: =Llegadas!$C$3
A12: Ítems marcados por día | B12: marcados ÷ días | C12: =Marca!$B$8/C11
A13: Segundos de atención por ítem | B13: costo por ítem ÷ costo por hora × 3600 | C13: ='Parámetros CSV'!$B$8/'Parámetros CSV'!$B$5*3600 | D13: supuesto de D20: preguntar al tutor
A14: Ítems que revisa un moderador por día | B14: 86400 ÷ segundos por ítem | C14: =86400/C13
A15: Moderadores por turno (c) | B15: CSV, valor base | C15: ='Parámetros CSV'!$B$6
A16: Ocupación de los moderadores ρ | B16: λ ÷ (c · μ) | C16: =C12/(C15*C14) | D16: con la escala de la muestra: por eso D7 bloquea
A17: Costo social por impresión nociva | B17: CSV | C17: ='Parámetros CSV'!$B$16
A18: Churn por impresión nociva | B18: tasa de churn × valor de marca | C18: ='Parámetros CSV'!$B$23*'Parámetros CSV'!$B$22
A19: Costo total de una impresión nociva | B19: social + churn | C19: =C17+C18 | D19: USD
A20: Ingreso de una impresión legítima | B20: CSV | C20: ='Parámetros CSV'!$B$4 | D20: USD
A21: Una nociva cuesta / una legítima rinde | C21: =C19/C20 | D21: veces
A22: Ingreso perdido al bajar una publicación buena | B22: medido, mediana | C22: 0.07 | D22: USD; 87 si es de un difusor masivo
A23: Costo de bajar una publicación buena | B23: reputacional + ingreso perdido | C23: ='Parámetros CSV'!$B$15+C22 | D23: USD
A24: Tipo de cambio | B24: publicación buena ÷ impresión nociva | C24: =C23/C19 | D24: impresiones nocivas que hay que evitar para pagar una publicación buena bajada

Sheet Diccionario
A1: Qué es cada columna
A2: RedBaires perdió la documentación de los campos: reconstruirla es parte de la nota.
A3: Columna | B3: Qué es | C3: Cómo lo sabemos | D3: Uso en el modelo
A4: event_id | B4: identificador del evento | C4: clave | D4: no entra
A5: cascade_id | B5: cascada a la que pertenece | C5: clave | D5: unidad de validación
A6: message_id | B6: pieza de contenido | C6: clave | D6: sin uso definido
A7: seed_flag | B7: marca el evento original | C7: dato | D7: llegadas y su tasa horaria
A8: forward_datetime | B8: fecha y hora del evento | C8: dato | D8: tasa de llegadas; 39 fechas en 2099
A9: actor_id | B9: cuenta que publica o reenvía | C9: dato | D9: 4.000 cuentas; no es entidad
A10: actor_follower_count | B10: seguidores | C10: dato | D10: impresiones = 0,15 × seguidores
A11: actor_following_count | B11: a cuántos sigue | C11: dato | D11: sin uso
A12: account_age_days | B12: antigüedad de la cuenta | C12: dato | D12: señal de coordinación; 514 anteriores a la plataforma
A13: verified_flag | B13: cuenta verificada | C13: dato | D13: probabilidad de remoción (D10)
A14: account_type_code | B14: BROADCASTER · CREATOR · AGGREGATOR · LURKER · STANDARD | C14: por los roles del enunciado | D14: el factor que más mueve R
... A33: moderation_latency_min | B33: minutos hasta la acción | C33: dato | D33: salida, no entrada: objetivo de validación

Sheet Limpieza
A1: Lo sucio de la muestra
A2: Qué hacer con cada problema es parte del modelo de datos.
A3: Problema | B3: Cuántos | C3: Qué se hace
A4: Filas duplicadas | B4: 132 | C4: se sacan
A5: Cascadas cortadas en exactamente 500 eventos (todas C2) | B5: 14 | C5: D14
A6: Mayúsculas mezcladas en formato, superficie e idioma | B6: 13850 | C6: se normalizan
A7: Faltantes en dwell_time_sec | B7: 2008
A8: Faltantes en sentiment_score | B8: 1347
A9: Faltantes en device_fingerprint_code | B9: 1327
A10: Faltantes en comments | B10: 937
A11: Faltantes en content_half_life_min | B11: 667
A12: Faltantes en impressions | B12: 625
A13: Fechas en 2099 | B13: 39
A14: Hijos anteriores al padre (inter_event_time_min negativo) | B14: 39
A15: Cuentas más viejas que la plataforma (opera desde 2013) | B15: 514
A16: Latencia de moderación mayor a 24 h | B16: 196
A17: dwell_time_sec negativo | B17: 66
A18: Cuentas con 0 seguidores | B18: 52
A19: Cuentas con más de un valor de seguidores (de 4.000) | B19: 3627 | C19: ¿seguidores al momento del evento?

Sheet Decisiones
A1: Decisiones D1 a D20
A2: Misma numeración que el README y el artifact. La columna amarilla es para lo que elija el grupo.
A3: D | B3: Decisión | C3: Opciones | D3: Propuesta | E3: Dato clave | F3: Elige el grupo
A4: D1 | B4: ¿Qué es la entidad? | C4: la cascada · un lote por generación · el reenvío | D4: la cascada (DECIDIDA 22/9) | E4: 139 min hasta la acción contra 43 entre generaciones | F4: la cascada
A5: D2 | B5: ¿Qué recursos tienen capacidad? | C5: sólo moderadores · moderadores y Centinela con cola | D5: sólo moderadores | E5: latencia contra carga: Spearman 0,022; piso de 90 min
A6: D3 | B6: Variables de decisión (mínimo 2) | C6: moderadores c · límite de reenvíos · degradación · agresividad del clasificador | D6: las tres del memo | E6: rangos en 'Parámetros CSV'
A7: D4 | B7: Variables de referencia (mínimo 2, contrapuestas) | C7: nocivas servidas · buenas bajadas · legítimas perdidas por fricción · ítems revisados × 0,12 · tiempo hasta la acción · alcance contra tamaño nocivo | D7: nocivas servidas + buenas bajadas (+ legítimas perdidas) | E7: 43 % de la cola es legítima; tipo de cambio en 'A priori'
A8: D5 | B8: Variables de estado (mínimo 2) | C8: ocupación (obligatoria) · largo de la cola · cascadas vivas e ítems en revisión · R efectivo | D8: ocupación + cola + cascadas vivas | E8: ocupación a escala de la muestra en 'A priori'
A9: D6 | B9: ¿Qué horizonte se simula? | C9: un mes + peor episodio · un solo episodio | D9: un mes + peor episodio | E9: pregunta al tutor
A10: D7 | B10: ¿Cuál es la escala? | C10: calibrar a 139 min · la muestra tal cual · proporción de 7,8 M | D10: calibrar a 139 min | E10: BLOQUEA: ocupación de 2 %
A11: D8 | B11: ¿Qué cuenta como nocivo? | C11: DISARM · umbral de toxicidad · los dos | D11: DISARM | E11: BLOQUEA: con DISARM, precisión 0,57 y recall 0,34 contra 0,72 y 0,63 del CSV
A12: D9 | B12: ¿Hay prioridad en la cola? | C12: FIFO + prioridad como escenario · sólo FIFO | D12: FIFO + escenario | E12: la espera no baja para lo más tóxico
A13: D10 | B13: ¿Cómo se aplica la remoción? | C13: fraccional · todo o nada · fraccional ponderado | D13: fraccional | E13: 11 % de hijos de un marcado nacen después de la acción
A14: D11 | B14: ¿Qué cuenta como coordinada? | C14: C2 + cuenta nueva · sólo C2 · por audiencia | D14: C2 + cuenta nueva | E14: C2: 42,8 eventos contra ~10; 13 % de cuentas nuevas contra 6 %
A15: D12 | B15: ¿Qué baja la degradación? | C15: factor de impresiones · R de las detectadas · los dos | D15: sin propuesta
A16: D13 | B16: ¿Sobre qué actúa el límite de reenvíos? | C16: por pieza · por generación · por cuenta | D16: por pieza | E16: umbral 1–20, reducción 0–0,9
A17: D14 | B17: ¿Qué se hace con las cascadas de 500? | C17: sacarlas y cortar la simulación en 500 · dejarlas | D17: sacarlas y cortar en 500 | E17: 14 cascadas, todas C2
A18: D15 | B18: ¿Cómo llegan los rumores? | C18: exponencial con tasa por hora · tasa constante | D18: tasa por hora | E18: hoja 'Llegadas'
A19: D16 | B19: ¿Cómo se sortean los hijos? | C19: Poisson(Λ) por generación · binomial negativa | D19: Poisson, y medir | E19: varianza / media 5,1; p99 188
A20: D17 | B20: ¿De qué tipos es el frente hijo? | C20: multinomial fija · condicionada al tipo del padre | D20: fija, y medir contra p99 | E20: hoja 'Tipos de cuenta'
A21: D18 | B21: ¿Decae por generación o por tiempo? | C21: por generación · por tiempo con vida media | D21: por generación | E21: hoja 'Generaciones'; vida media contra tamaño 0,04
A22: D19 | B22: ¿Tiempo entre generaciones? | C22: gamma · exponencial · empírica | D22: sin propuesta | E22: hoja 'Ajuste D19': no puede ser Erlang
A23: D20 | B23: ¿Cuánto tarda una revisión? | C23: Erlang(k, ~20 s) · tiempo fijo · sensibilidad | D23: Erlang(k, ~20 s) | E23: segundos por ítem en 'A priori'
